lib/__init__.py
lib/akshita.py
Topsis1_akshita_102103470-0.0.1.dist-info/METADATA
Topsis1_akshita_102103470-0.0.1.dist-info/WHEEL
Topsis1_akshita_102103470-0.0.1.dist-info/top_level.txt
Topsis1_akshita_102103470-0.0.1.dist-info/RECORD
